src/assembly_line/__init__.py
cdev_assembly_line-0.0.1.dist-info/WHEEL
cdev_assembly_line-0.0.1.dist-info/METADATA
cdev_assembly_line-0.0.1.dist-info/RECORD
