Metadata-Version: 2.1
Name: cdev-assembly-line
Version: 0.0.1
Summary: Tool for generating Pypi ready Python Projects
Author: Daniel Sanchez
Author-email: 15sanchd@gmail.com
Requires-Python: >=3.7,<4.0
Classifier: Programming Language :: Python :: 3
Classifier: Programming Language :: Python :: 3.7
Classifier: Programming Language :: Python :: 3.8
Classifier: Programming Language :: Python :: 3.9
Classifier: Programming Language :: Python :: 3.10
